CHANGELOG.md
LICENSE
README.md
chcli/__init__.py
chcli/cli.py
chcli/common.py
chcli/completion.py
chcli/connection.py
chcli/console.py
chcli/constants.py
chcli/executer.py
chcli/grammar/ClickHouseLexer.g4
chcli/grammar/ClickHouseLexer.interp
chcli/grammar/ClickHouseLexer.py
chcli/grammar/ClickHouseLexer.tokens
chcli/grammar/ClickHouseParser.g4
chcli/grammar/ClickHouseParser.interp
chcli/grammar/ClickHouseParser.py
chcli/grammar/ClickHouseParser.tokens
chcli/grammar/ClickHouseParserListener.py
chcli/grammar/ClickHouseParserVisitor.py
chcli/grammar/__init__.py
chcli/key_bindings.py
chcli-0.1.0.dist-info/entry_points.txt
chcli-0.1.0.dist-info/LICENSE
chcli-0.1.0.dist-info/WHEEL
chcli-0.1.0.dist-info/METADATA
chcli-0.1.0.dist-info/RECORD
