Metadata-Version: 2.1
Name: chcli
Version: 0.1.0
Summary: A Terminal Client for ClickHouse with AutoCompletion and Syntax Highlighting.
Home-page: https://github.com/long2ice/chcli
License: Apache-2.0
Keywords: migrate,Tortoise-ORM,mysql
Author: long2ice
Author-email: long2ice@gmail.com
Requires-Python: >=3.8,<4.0
Classifier: License :: OSI Approved :: Apache Software License
Classifier: Programming Language :: Python :: 3
Classifier: Programming Language :: Python :: 3.8
Requires-Dist: antlr4-python3-runtime
Requires-Dist: async_lru
Requires-Dist: asynch
Requires-Dist: click
Requires-Dist: prompt_toolkit
Requires-Dist: rich
Requires-Dist: sqlparse
Project-URL: Documentation, https://github.com/long2ice/chcli
Project-URL: Repository, https://github.com/long2ice/chcli.git
